aida_tools/__init__.py
aida_tools/importer.py
aida_tools/utils.py
cli/__init__.py
cli/autpe/app.py
cli/autpe/config.py
cli/importer.py
cli/tommasoli/app.py
cli/tommasoli/config.py
models/__init__.py
models/attachment.py
models/autpe.py
models/autpe_has_item.py
models/autpe_has_place.py
models/date.py
models/db.py
models/folder.py
models/item.py
models/item_has_place.py
models/log_form.py
models/medium.py
models/mult_value.py
models/names.py
models/ogt_d.py
models/stcc_d.py
aida_tools-0.1.3.dist-info/entry_points.txt
aida_tools-0.1.3.dist-info/METADATA
aida_tools-0.1.3.dist-info/WHEEL
aida_tools-0.1.3.dist-info/RECORD
