Metadata-Version: 2.1
Name: aida-tools
Version: 0.1.3
Summary: 
License: MIT
Author: Matteo Spanio
Author-email: dev2@audioinnova.com
Requires-Python: >=3.11,<4.0
Classifier: License :: OSI Approved :: MIT License
Classifier: Programming Language :: Python :: 3
Classifier: Programming Language :: Python :: 3.11
Requires-Dist: mariadb (>=1.1.6,<2.0.0)
Requires-Dist: rich (>=13.3.5,<14.0.0)
